booster/__init__.py
hellogoodbye/__init__.py
hellogoodbye/__main__.py
hellogoodbye-0.0.2.dist-info/DESCRIPTION.rst
hellogoodbye-0.0.2.dist-info/METADATA
hellogoodbye-0.0.2.dist-info/RECORD
hellogoodbye-0.0.2.dist-info/WHEEL
hellogoodbye-0.0.2.dist-info/entry_points.txt
hellogoodbye-0.0.2.dist-info/metadata.json
hellogoodbye-0.0.2.dist-info/top_level.txt
helloworld/__init__.py
helloworld/__main__.py
