Metadata-Version: 2.0
Name: hellogoodbye
Version: 0.0.2
Summary: Hello, and good-bye!
Home-page: UNKNOWN
Author: Yusuke Sugomori
Author-email: me@yusugomori.com
License: UNKNOWN
Platform: UNKNOWN
Classifier: Development Status :: 1 - Planning
